koroman/__init__.py
koroman/core.py
koroman-1.0.0.dist-info/licenses/LICENSE
koroman-1.0.0.dist-info/METADATA
koroman-1.0.0.dist-info/WHEEL
koroman-1.0.0.dist-info/top_level.txt
koroman-1.0.0.dist-info/RECORD
