Metadata-Version: 2.4
Name: koroman
Version: 1.0.0
Summary: Korean Romanizer with pronunciation rules based on 국립국어원 표기법
Home-page: https://github.com/gerosyab/koroman
Author: Donghe Youn (Daissue)
Author-email: gerosyab@gmail.com
Project-URL: Bug Reports, https://github.com/gerosyab/koroman/issues
Project-URL: Source, https://github.com/gerosyab/koroman
Keywords: korean,romanizer,romanization,hangul,transliteration,linguistics,korean romanizer,korean romanization,korean transliteration,korean linguistics,koroman
Classifier: Development Status :: 5 - Production/Stable
Classifier: Intended Audience :: Developers
Classifier: Topic :: Software Development :: Libraries :: Python Modules
Classifier: Topic :: Text Processing :: Linguistic
Classifier: Programming Language :: Python :: 3
Classifier: Programming Language :: Python :: 3.6
Classifier: Programming Language :: Python :: 3.7
Classifier: Programming Language :: Python :: 3.8
Classifier: Programming Language :: Python :: 3.9
Classifier: License :: OSI Approved :: MIT License
Classifier: Operating System :: OS Independent
Requires-Python: >=3.6
License-File: LICENSE
Dynamic: author
Dynamic: author-email
Dynamic: classifier
Dynamic: description
Dynamic: description-content-type
Dynamic: home-page
Dynamic: keywords
Dynamic: license-file
Dynamic: project-url
Dynamic: requires-python
Dynamic: summary
